.gitignore
MANIFEST.in
README.rst
README.txt
bootstrap.py
buildout-plone4.cfg
setup.py
collective/__init__.py
collective.contentrules.mailtolocalrole.egg-info/PKG-INFO
collective.contentrules.mailtolocalrole.egg-info/SOURCES.txt
collective.contentrules.mailtolocalrole.egg-info/dependency_links.txt
collective.contentrules.mailtolocalrole.egg-info/entry_points.txt
collective.contentrules.mailtolocalrole.egg-info/namespace_packages.txt
collective.contentrules.mailtolocalrole.egg-info/not-zip-safe
collective.contentrules.mailtolocalrole.egg-info/requires.txt
collective.contentrules.mailtolocalrole.egg-info/top_level.txt
collective/contentrules/__init__.py
collective/contentrules/mailtolocalrole/HISTORY.txt
collective/contentrules/mailtolocalrole/TODO.txt
collective/contentrules/mailtolocalrole/__init__.py
collective/contentrules/mailtolocalrole/configure.zcml
collective/contentrules/mailtolocalrole/rebuild_i18n.sh
collective/contentrules/mailtolocalrole/version.txt
collective/contentrules/mailtolocalrole/actions/__init__.py
collective/contentrules/mailtolocalrole/actions/configure.zcml
collective/contentrules/mailtolocalrole/actions/mail.py
collective/contentrules/mailtolocalrole/actions/vocabularies.py
collective/contentrules/mailtolocalrole/locales/collective.contentrules.mailtolocalrole.pot
collective/contentrules/mailtolocalrole/locales/it/LC_MESSAGES/collective.contentrules.mailtolocalrole.mo
collective/contentrules/mailtolocalrole/locales/it/LC_MESSAGES/collective.contentrules.mailtolocalrole.po
collective/contentrules/mailtolocalrole/locales/nl/LC_MESSAGES/collective.contentrules.mailtolocalrole.mo
collective/contentrules/mailtolocalrole/locales/nl/LC_MESSAGES/collective.contentrules.mailtolocalrole.po
collective/contentrules/mailtolocalrole/tests/__init__.py
collective/contentrules/mailtolocalrole/tests/test_action_mailtolocalrole.py