Metadata-Version: 1.0
Name: collective.contentrules.mailtolocalrole
Version: 1.3
Summary: Send e-mail to users having a localrole on the object
Home-page: http://plone.org/products/collective-contentrules-mailtolocalrole
Author: Zest Software (Fred van Dijk)
Author-email: info@zestsoftware.nl
License: GPL
Keywords: plone contentrules action mail
Platform: UNKNOWN
Classifier: Programming Language :: Python
Classifier: Topic :: Software Development :: Libraries :: Python Modules
